bettertogether/__init__.py
bettertogether/py.typed
bettertogether-0.0.2.dist-info/METADATA
bettertogether-0.0.2.dist-info/WHEEL
bettertogether-0.0.2.dist-info/top_level.txt
bettertogether-0.0.2.dist-info/RECORD
