Metadata-Version: 2.4
Name: bettertogether
Version: 0.0.2
Summary: Library for composing prompt and weight optimization algorithms for compound AI systems.
Author-email: Dilara Soylu <soylu@stanford.edu>
Project-URL: Homepage, https://github.com/dilarasoylu/bettertogether
Project-URL: Issues, https://github.com/dilarasoylu/bettertogether/issues
Classifier: Programming Language :: Python :: 3
Classifier: License :: OSI Approved :: MIT License
Classifier: Development Status :: 3 - Alpha
Requires-Python: >=3.11
